anyschema/__init__.py
anyschema/_anyschema.py
anyschema/_dependencies.py
anyschema/_utils.py
anyschema/adapters.py
anyschema/exceptions.py
anyschema/py.typed
anyschema/typing.py
anyschema/parsers/__init__.py
anyschema/parsers/_annotated.py
anyschema/parsers/_base.py
anyschema/parsers/_builtin.py
anyschema/parsers/_forward_ref.py
anyschema/parsers/_union.py
anyschema/parsers/annotated_types.py
anyschema/parsers/attrs.py
anyschema/parsers/pydantic.py
anyschema-0.2.1.dist-info/METADATA
anyschema-0.2.1.dist-info/WHEEL
anyschema-0.2.1.dist-info/licenses/LICENSE
anyschema-0.2.1.dist-info/RECORD
