Metadata-Version: 2.4
Name: anyschema
Version: 0.2.1
Summary: From type specifications to dataframe schemas
Project-URL: Homepage, https://github.com/fbruzzesi/anyschema
Project-URL: Documentation, https://fbruzzesi.github.io/anyschema/
Project-URL: Repository, https://github.com/fbruzzesi/anyschema
Project-URL: Issue Tracker, https://github.com/fbruzzesi/anyschema/issues
Author: Francesco Bruzzesi
License:                                  Apache License
License-File: LICENSE
Classifier: Development Status :: 3 - Alpha
Classifier: License :: OSI Approved :: Apache Software License
Classifier: Operating System :: OS Independent
Classifier: Programming Language :: Python
Classifier: Programming Language :: Python :: 3
Classifier: Programming Language :: Python :: 3.10
Classifier: Programming Language :: Python :: 3.11
Classifier: Programming Language :: Python :: 3.12
Classifier: Programming Language :: Python :: 3.13
Classifier: Programming Language :: Python :: 3.14
Classifier: Typing :: Typed
Requires-Python: >=3.10
Requires-Dist: narwhals>=2.0.0
Requires-Dist: typing-extensions>=4.14.0
Provides-Extra: attrs
Requires-Dist: attrs>=22.1.0; extra == 'attrs'
Provides-Extra: pydantic
Requires-Dist: pydantic>=2.0.0; extra == 'pydantic'
